maxheap/__init__.py
maxheap/maxheap.py
maxheapq-0.0.4.dist-info/LICENSE
maxheapq-0.0.4.dist-info/METADATA
maxheapq-0.0.4.dist-info/WHEEL
maxheapq-0.0.4.dist-info/top_level.txt
maxheapq-0.0.4.dist-info/RECORD
