Metadata-Version: 2.1
Name: maxheapq
Version: 0.0.4
Summary: Maxheap
Home-page: https://github.com/mshelll/maxheap
Author: Marshel Abraham
Author-email: marshel.abraham@gmail.com
License: UNKNOWN
Project-URL: Bug Tracker, https://github.com/mshelll/maxheap/issues
Platform: UNKNOWN
Classifier: Programming Language :: Python :: 3
Classifier: License :: OSI Approved :: MIT License
Classifier: Operating System :: OS Independent
Requires-Python: >=3.6
License-File: LICENSE
